rn4s/__init__.py
rn4s/agent.py
rn4s/execution.py
rn4s/formatting.py
rn4s/judge.py
rn4s/model.py
rn4s/reasoning.py
rn4s/tools.py
rn4s/client/__init__.py
rn4s/client/base_client.py
rn4s/client/huggingface_client.py
rn4s/client/litellm_client.py
rn4s/client/openrouter_client.py
rn4s/client/sambanova_client.py
rn4s/client/sambanova_response.py
rn4s-0.1.2.dist-info/licenses/LICENSE
rn4s-0.1.2.dist-info/METADATA
rn4s-0.1.2.dist-info/WHEEL
rn4s-0.1.2.dist-info/top_level.txt
rn4s-0.1.2.dist-info/RECORD
